atenrich/__init__.py
atenrich/calculate_enrichment.py
atenrich/convert_clustering_to_classification.py
atenrich/generate_feature_matrix.py
atenrich/rank_features.py
atenrich/data/genelists/baena-gonzalez2007_AKIN10_induced.genelist
atenrich/data/genelists/baena-gonzalez2007_AKIN10_repressed.genelist
atenrich/data/genelists/bethke2009_ERF104ox_down.genelist
atenrich/data/genelists/bethke2009_ERF104ox_up.genelist
atenrich/data/genelists/bhargava2013_CK_down.genelist
atenrich/data/genelists/bhargava2013_CK_up.genelist
atenrich/data/genelists/birkenbihl2016_WRKY18_chip_seq.genelist
atenrich/data/genelists/birkenbihl2016_WRKY33_chip_seq.genelist
atenrich/data/genelists/birkenbihl2016_WRKY40_chip_seq.genelist
atenrich/data/genelists/blasing2005_carbon_fixation_induced.genelist
atenrich/data/genelists/blasing2005_carbon_fixation_repressed.genelist
atenrich/data/genelists/blasing2005_glucose_induced.genelist
atenrich/data/genelists/blasing2005_glucose_repressed.genelist
atenrich/data/genelists/blasing2005_mannitol_induced.genelist
atenrich/data/genelists/blasing2005_mannitol_repressed.genelist
atenrich/data/genelists/blasing2005_rhythmic.genelist
atenrich/data/genelists/blasing2005_sucrose_induced.genelist
atenrich/data/genelists/blasing2005_sucrose_repressed.genelist
atenrich/data/genelists/busch2010_WUS_chip_chip.genelist
atenrich/data/genelists/chang2013_EIN3_NR.genelist
atenrich/data/genelists/chang2013_EIN3_R.genelist
atenrich/data/genelists/cheminant2011_ga1_DELLA_global_down.genelist
atenrich/data/genelists/cheminant2011_ga1_DELLA_global_up.genelist
atenrich/data/genelists/cheminant2011_ga1_down.genelist
atenrich/data/genelists/cheminant2011_ga1_up.genelist
atenrich/data/genelists/chen2014_FHY1_chip_seq.genelist
atenrich/data/genelists/chen2014_phyA_chip_seq.genelist
atenrich/data/genelists/chen2014_phyA_induced.genelist
atenrich/data/genelists/chen2014_phyA_repressed.genelist
atenrich-0.2.2.dist-info/DESCRIPTION.rst
atenrich-0.2.2.dist-info/METADATA
atenrich-0.2.2.dist-info/RECORD
atenrich-0.2.2.dist-info/WHEEL
atenrich-0.2.2.dist-info/metadata.json
atenrich-0.2.2.dist-info/top_level.txt
