Metadata-Version: 2.0
Name: atenrich
Version: 0.2.2
Summary: UNKNOWN
Home-page: UNKNOWN
Author: UNKNOWN
Author-email: UNKNOWN
License: UNKNOWN
Platform: UNKNOWN
Requires-Dist: Click
Requires-Dist: numpy
Requires-Dist: pandas
Requires-Dist: scipy
